renfe_cli-5.2.0.dist-info/METADATA
renfe_cli-5.2.0.dist-info/WHEEL
renfe_cli-5.2.0.dist-info/entry_points.txt
renfe_cli-5.2.0.dist-info/licenses/LICENSE
renfe_cli/__init__.py
renfe_cli/renfe_cli.abi3.so
renfe_cli-5.2.0.dist-info/RECORD
