Metadata-Version: 2.3
Name: renfe-cli
Version: 5.2.0
Classifier: Programming Language :: Rust
Classifier: Programming Language :: Python :: Implementation :: CPython
Classifier: Programming Language :: Python :: Implementation :: PyPy
Classifier: Development Status :: 4 - Beta
Classifier: Environment :: Console
Classifier: Intended Audience :: End Users/Desktop
Classifier: Intended Audience :: Developers
Classifier: License :: OSI Approved :: BSD License
Classifier: Operating System :: MacOS
Classifier: Operating System :: Unix
Classifier: Operating System :: POSIX
Classifier: Operating System :: Microsoft :: Windows
Classifier: Topic :: Utilities
Classifier: Topic :: Terminals
License-File: LICENSE
Summary: Get faster Renfe Spanish Trains timetables in your terminal.
Keywords: timetables,schedules,trains,renfe,cli,rust,python,pyo3,maturin
Home-Page: https://github.com/gerardcl/renfe-cli
Author: Gerard C.L. <gerardcl@gmail.com>
Author-email: Gerard Castillo Lasheras <gerardcl@gmail.com>
Maintainer-email: Gerard Castillo Lasheras <gerardcl@gmail.com>
License: BSD-3-Clause
Requires-Python: >=3.8
Project-URL: Homepage, https://github.com/gerardcl/renfe-cli
Project-URL: Documentation, https://github.com/gerardcl/renfe-cli
Project-URL: Repository, https://github.com/gerardcl/renfe-cli
Project-URL: Issues, https://github.com/gerardcl/renfe-cli/issues
Project-URL: Changelog, https://github.com/gerardcl/renfe-cli/blob/master/CHANGELOG.md
